[{"uuid":"168DB59494EB4C2CA13871AFD8EBE8F1","dateTime":"01 February 2023 04:26","randomDecimal1":32.6975,"randomDecimal2":81.3959,"dividedResult":2.489361572,"roundedResult":2.49,"calculationResult":"generated random decimals are 32.6975 and 81.3959.\nResult of division is 81.3959 / 32.6975 = 2.4893615720\nRounded value is 2.49","md5Hash":"10baea194b8f05e13601c7381768bc59"},{"uuid":"D927851D92A94C51B7B4D1F783347D7C","dateTime":"01 February 2023 04:36","randomDecimal1":22.7803,"randomDecimal2":75.089,"dividedResult":3.2962252473,"roundedResult":3.3,"calculationResult":"generated random decimals are 22.7803 and 75.089.\nResult of division is 75.089 / 22.7803 = 3.2962252473\nRounded value is 3.30","md5Hash":"b7328e46b10cc8768e63ef7a0a96f074"},{"uuid":"CCD62FA0817F48CC86AB26D20D938BBA","dateTime":"01 February 2023 04:37","randomDecimal1":88.8562,"randomDecimal2":71.0957,"dividedResult":1.2498111701,"roundedResult":1.25,"calculationResult":"generated random decimals are 88.8562 and 71.0957.\nResult of division is 88.8562 / 71.0957 = 1.2498111701\nRounded value is 1.25","md5Hash":"cb4bd1610491091adcac0ad9e93e9cbc"},{"uuid":"A040089DF5AC409EB7D6FA908CBAF0BF","dateTime":"01 February 2023 04:37","randomDecimal1":5.9471,"randomDecimal2":35.2527,"dividedResult":5.9277126667,"roundedResult":5.93,"calculationResult":"generated random decimals are 5.9471 and 35.2527.\nResult of division is 35.2527 / 5.9471 = 5.9277126667\nRounded value is 5.93","md5Hash":"c7362de65ca3e4d962d6c03ef16960e0"},{"uuid":"32AFC0925EDA4422AF27C30A6B7DA9E2","dateTime":"01 February 2023 04:40","randomDecimal1":37.6154,"randomDecimal2":68.2136,"dividedResult":1.8134487471,"roundedResult":1.82,"calculationResult":"generated random decimals are 37.6154 and 68.2136.\nResult of division is 68.2136 / 37.6154 = 1.8134487471\nRounded value is 1.82","md5Hash":"9ef19a00ad5982d04bf64141d7ff8bf4"},{"uuid":"1BAA822CC215450CA276DD73D91C5405","dateTime":"01 February 2023 04:40","randomDecimal1":8.714,"randomDecimal2":58.6391,"dividedResult":6.7292976819,"roundedResult":6.73,"calculationResult":"generated random decimals are 8.714 and 58.6391.\nResult of division is 58.6391 / 8.714 = 6.7292976819\nRounded value is 6.73","md5Hash":"50c9203897099b7c6bcc4595458b53c2"},{"uuid":"664DF40D41CC46C9B2D375C9F5FEC712","dateTime":"01 February 2023 04:40","randomDecimal1":19.9624,"randomDecimal2":12.5642,"dividedResult":1.5888317601,"roundedResult":1.59,"calculationResult":"generated random decimals are 19.9624 and 12.5642.\nResult of division is 19.9624 / 12.5642 = 1.5888317601\nRounded value is 1.59","md5Hash":"71b0f5664c5ec2f65d5515976a9598e6"},{"uuid":"D8F35175ED074E73A2FA2AE32F23CB04","dateTime":"01 February 2023 04:41","randomDecimal1":10.009,"randomDecimal2":2.0738,"dividedResult":4.8264056322,"roundedResult":4.83,"calculationResult":"generated random decimals are 10.009 and 2.0738.\nResult of division is 10.009 / 2.0738 = 4.8264056322\nRounded value is 4.83","md5Hash":"1d3f1ae45c44bcb7df932929c08897d9"},{"uuid":"8ADC63D52F1646D5BF83F9EC26444D93","dateTime":"01 February 2023 04:42","randomDecimal1":56.8163,"randomDecimal2":32.1433,"dividedResult":1.7675938688,"roundedResult":1.77,"calculationResult":"generated random decimals are 56.8163 and 32.1433.\nResult of division is 56.8163 / 32.1433 = 1.7675938688\nRounded value is 1.77","md5Hash":"1f08e23e3faf2ceb52e20ca961abd384"},{"uuid":"E45BD50F4B694F10A20D4EAEEE415E57","dateTime":"01 February 2023 04:42","randomDecimal1":68.0655,"randomDecimal2":17.6585,"dividedResult":3.8545459694,"roundedResult":3.86,"calculationResult":"generated random decimals are 68.0655 and 17.6585.\nResult of division is 68.0655 / 17.6585 = 3.8545459694\nRounded value is 3.86","md5Hash":"0196cb92e5b5c7df067d509c8358ce68"},{"uuid":"2423972E41B84EC08B1026616F403806","dateTime":"01 February 2023 04:44","randomDecimal1":4.7263,"randomDecimal2":95.5256,"dividedResult":20.2114973659,"roundedResult":20.22,"calculationResult":"generated random decimals are 4.7263 and 95.5256.\nResult of division is 95.5256 / 4.7263 = 20.2114973659\nRounded value is 20.22","md5Hash":"9255e3ffdb9ff9045bea971b596a939d"}]